[
  {
    "CodigoProducto": "FOU123",
    "ClienteCUIT": "20-11111111-5",
    "Ubicacion": "4,11,2",
    "Cantidad": 100
  },
  {
    "CodigoProducto": "FOU456",
    "ClienteCUIT": "20-11111111-5",
    "Ubicacion": "8,5,1",
    "Cantidad": 50
  },
  {
    "CodigoProducto": "FOU789",
    "ClienteCUIT": "20-11111111-5",
    "Ubicacion": "12,17,3",
    "Cantidad": 75
  },
  {
    "CodigoProducto": "EIG321",
    "ClienteCUIT": "20-22222222-5",
    "Ubicacion": "3,9,5",
    "Cantidad": 30
  },
  {
    "CodigoProducto": "EIG654",
    "ClienteCUIT": "20-22222222-5",
    "Ubicacion": "7,4,2",
    "Cantidad": 20
  },
  {
    "CodigoProducto": "EIG987",
    "ClienteCUIT": "20-22222222-5",
    "Ubicacion": "3,5,6",
    "Cantidad": 15
  }
]
